simple_deepmoji
