Metadata-Version: 1.0
Name: simple-deepmoji
Version: 0.1.1
Summary: DeepMoji python library
Home-page: https://github.com/JarbasAl/simple_deepmoji
Author: jarbasAI
Author-email: jarbasai@mailfence.com
License: UNKNOWN
Platform: UNKNOWN
